tests/__init__.py
tests/tmx2dataframe_test.py
tmx2dataframe/__init__.py
tmx2dataframe/tmx2dataframe.py
tmx2dataframe-0.3.0.dist-info/LICENSE.md
tmx2dataframe-0.3.0.dist-info/METADATA
tmx2dataframe-0.3.0.dist-info/WHEEL
tmx2dataframe-0.3.0.dist-info/top_level.txt
tmx2dataframe-0.3.0.dist-info/RECORD
