Metadata-Version: 2.1
Name: tmx2dataframe
Version: 0.3.0
Summary: Converting tmx translation files to pandas dataframe
Home-page: http://github.com/jaderabbit/tmx2dataframe
Author: Jade Abbott
Author-email: jade.zoe.abbott@gmail.com
License: MIT
Platform: UNKNOWN
Classifier: Programming Language :: Python :: 3
Classifier: License :: OSI Approved :: MIT License
Classifier: Operating System :: OS Independent
